markdown_typst/__init__.py
markdown_typst/typst_extension.py
markdown_typst-0.1.4.dist-info/licenses/LICENSE
markdown_typst-0.1.4.dist-info/METADATA
markdown_typst-0.1.4.dist-info/WHEEL
markdown_typst-0.1.4.dist-info/entry_points.txt
markdown_typst-0.1.4.dist-info/top_level.txt
markdown_typst-0.1.4.dist-info/RECORD
