Metadata-Version: 2.4
Name: markdown-typst
Version: 0.1.4
Summary: A Markdown extension to compile typst code blocks to SVG.
Home-page: https://github.com/eWloYW8/markdown-typst
Author: eWloYW8
Author-email: 3171132517@qq.com
License: MIT
Classifier: Programming Language :: Python :: 3
Classifier: License :: Public Domain
Classifier: Operating System :: OS Independent
Requires-Python: >=3.6
License-File: LICENSE
Requires-Dist: markdown
Requires-Dist: typst
Dynamic: author
Dynamic: author-email
Dynamic: classifier
Dynamic: description
Dynamic: description-content-type
Dynamic: home-page
Dynamic: license
Dynamic: license-file
Dynamic: requires-dist
Dynamic: requires-python
Dynamic: summary
